Workbook

Sheet READ_ME
B2: ASIA CROSS-ASSET OUTLOOK — 3-SLIDE CHART PACK
B3: China / HK / Korea / Japan / Taiwan
B5: COLOUR LEGEND
B6: Blue text on yellow fill | C6: HARDCODED INPUT — replace with your own terminal data. These are the only cells you should edit.
B7: Black text | C7: Formula. Do not overwrite — it recalculates from the inputs.
B8: Green text | C8: Link to another sheet in this workbook.
B10: IMPORTANT — DATA STATUS
C11: ALL market data in this workbook is ILLUSTRATIVE PLACEHOLDER. It is NOT live market data.
C12: It exists so the charts render with correct shape, scale and formatting. Replace every yellow cell
C13: with Bloomberg / Refinitiv / FactSet pulls before this leaves your desk.
C15: The CATL fundamental data on the S1 sector tab IS real and sourced — see the source column.
B17: SHEET MAP
B18: S1_Equities | C18: Slide 1 — 3 charts: fwd P/E vs 5Y band | 3M EPS revision ratio | sector fwd P/E vs EPS growth
B19: S2_FixedIncome | C19: Slide 2 — 3 charts: 10Y real yields | BOJ OIS path vs core-core CPI | curve slope vs 5Y range
B20: S3_CrossAsset | C20: Slide 3 — ERP by market (links to S1 + S2) + OW/UW positioning table
B22: THESIS SPINE (do not put trade names on these 3 slides)
C23: S1 title: 'Valuation gap narrowing as China earnings inflect' -> sets up the equity OW
C24: S2 title: 'Japan the last major curve yet to normalise' -> sets up the JGB curve trade
C25: S3 title: 'Where the risk premium sits' -> asset-class OW/UW only
B27: UNRESOLVED — READ BEFORE BUILDING
C28: S2 as built tells a BOJ-NORMALISATION / inflation-persistent story. That is a BEAR steepener setup
C29: (long end sells off). If the trade is genuinely a BULL steepener (front end rallies on dovish repricing),
C30: this slide contradicts it AND contradicts the constructive equity case on S1. Pin this down first:
C31: - Bear steepener -> keep S2 as built. Lead with OIS vs CPI. Book reads directionally aligned.
C32: - Bull steepener -> rebuild S2 on a growth-slowdown / risk-hedge spine, and label the trade a HEDGE on S3.

Sheet S1_Equities
B2: SLIDE 1 — EQUITIES
B3: Valuation gap narrowing as China earnings inflect
B6: CHART 1 — 12M FORWARD P/E vs 5Y MEAN AND +/-1SD
B7: Index | C7: Current fwd P/E | D7: 5Y mean | E7: 5Y st.dev | F7: -1SD | G7: +1SD | H7: Z-score
B8: CSI 300 | C8: 13.5 | D8: 12 | E8: 1.8 | F8: =D8-E8 -> 10.2 | G8: =D8+E8 -> 13.8 | H8: =IF(E8=0,"",(C8-D8)/E8) -> 0.83333333
B9: HSCEI | C9: 10.5 | D9: 9.5 | E9: 1.5 | F9: =D9-E9 -> 8 | G9: =D9+E9 -> 11 | H9: =IF(E9=0,"",(C9-D9)/E9) -> 0.66666667
B10: KOSPI | C10: 11 | D10: 10.5 | E10: 2 | F10: =D10-E10 -> 8.5 | G10: =D10+E10 -> 12.5 | H10: =IF(E10=0,"",(C10-D10)/E10) -> 0.25
B11: TOPIX | C11: 16 | D11: 14.5 | E11: 1.4 | F11: =D11-E11 -> 13.1 | G11: =D11+E11 -> 15.9 | H11: =IF(E11=0,"",(C11-D11)/E11) -> 1.0714286
B12: TWSE (MSCI Taiwan) | C12: 17.5 | D12: 15 | E12: 2.5 | F12: =D12-E12 -> 12.5 | G12: =D12+E12 -> 17.5 | H12: =IF(E12=0,"",(C12-D12)/E12) -> 1
B13: Sort ascending by Z-score before it goes on the slide — China/HK land on the left and the eye reads cheap-to-expensive.
B16: CHART 2 — 3M EPS REVISION RATIO AND CONSENSUS EPS GROWTH
B17: Index | C17: 3M revision ratio | D17: FY26E EPS growth | E17: FY27E EPS growth | F17: 2Y CAGR
B18: CSI 300 | C18: 1.15 | D18: 0.14 | E18: 0.135 | F18: =IFERROR(((1+D18)*(1+E18))^0.5-1,"") -> 0.13749725
B19: HSCEI | C19: 1.08 | D19: 0.12 | E19: 0.11 | F19: =IFERROR(((1+D19)*(1+E19))^0.5-1,"") -> 0.11498879
B20: KOSPI | C20: 1.22 | D20: 0.25 | E20: 0.18 | F20: =IFERROR(((1+D20)*(1+E20))^0.5-1,"") -> 0.21449578
B21: TOPIX | C21: 0.95 | D21: 0.08 | E21: 0.07 | F21: =IFERROR(((1+D21)*(1+E21))^0.5-1,"") -> 0.074988372
B22: TWSE (MSCI Taiwan) | C22: 1.3 | D22: 0.22 | E22: 0.16 | F22: =IFERROR(((1+D22)*(1+E22))^0.5-1,"") -> 0.18962179
B23: Revision ratio = analyst upgrades / downgrades over 3M. Above 1.0 = net upgrades. Order the x-axis by this column, not alphabetically.
B26: CHART 3 — SECTOR LAYER: FWD P/E vs FY26E EPS GROWTH
B27: Sector basket | C27: Fwd P/E | D27: FY26E EPS growth | E27: PEG | F27: Source / note
B28: MSCI China Industrials | C28: 14 | D28: 0.15 | E28: =IFERROR(C28/(D28*100),"") -> 0.93333333 | F28: Illustrative
B29: MSCI China Materials | C29: 12 | D29: 0.1 | E29: =IFERROR(C29/(D29*100),"") -> 1.2 | F29: Illustrative
B30: MSCI Korea IT | C30: 13 | D30: 0.3 | E30: =IFERROR(C30/(D30*100),"") -> 0.43333333 | F30: Illustrative
B31: MSCI Taiwan IT | C31: 18 | D31: 0.24 | E31: =IFERROR(C31/(D31*100),"") -> 0.75 | F31: Illustrative
B32: MSCI Japan Industrials | C32: 17 | D32: 0.075 | E32: =IFERROR(C32/(D32*100),"") -> 2.2666667 | F32: Illustrative
B33: This is the chart that legitimises the single-name idea as a broad regional theme. Keep it sector-level — no tickers on this slide.

Sheet S2_FixedIncome
B2: SLIDE 2 — FIXED INCOME
B3: Japan the last major curve yet to normalise
B6: CHART 1 — 10Y REAL YIELD (NOMINAL LESS CORE CPI)
B7: Market | C7: 10Y nominal | D7: Core CPI YoY | E7: 10Y real yield | F7: Policy rate
B8: China (CGB) | C8: 0.019 | D8: 0.005 | E8: =C8-D8 -> 0.014 | F8: 0.013
B9: Hong Kong (HKGB) | C9: 0.034 | D9: 0.015 | E9: =C9-D9 -> 0.019 | F9: 0.04
B10: Korea (KTB) | C10: 0.031 | D10: 0.02 | E10: =C10-D10 -> 0.011 | F10: 0.025
B11: Japan (JGB) | C11: 0.019 | D11: 0.025 | E11: =C11-D11 -> -0.006 | F11: 0.0075
B12: Taiwan (TWGB) | C12: 0.016 | D12: 0.016 | E12: =C12-D12 -> 0 | F12: 0.02
B13: Japan prints the only negative real yield of the five. That single bar plants 'Japan rates are mispriced' as a regional observation, not a trade pitch.
B16: CHART 2 — BOJ OIS-IMPLIED PATH vs CORE-CORE CPI
B17: Month | C17: BOJ policy rate | D17: OIS 1Y fwd | E17: Core-core CPI YoY | F17: Shunto (annual)
B18: Feb-25 | C18: 0.005 | D18: 0.0075 | E18: 0.025
B19: Apr-25 | C19: 0.005 | D19: 0.008 | E19: 0.0255 | F19: 0.0533
B20: Jun-25 | C20: 0.005 | D20: 0.0085 | E20: 0.026
B21: Aug-25 | C21: 0.005 | D21: 0.009 | E21: 0.0258
B22: Oct-25 | C22: 0.005 | D22: 0.0095 | E22: 0.0262
B23: Dec-25 | C23: 0.005 | D23: 0.01 | E23: 0.0265
B24: Feb-26 | C24: 0.0075 | D24: 0.011 | E24: 0.0268
B25: Apr-26 | C25: 0.0075 | D25: 0.0115 | E25: 0.027 | F25: 0.0545
B26: Jun-26 | C26: 0.0075 | D26: 0.012 | E26: 0.0262
B27: Aug-26 | C27: 0.0075 | D27: 0.0125 | E27: 0.0255
B29: Extend the rows to your full window. Shunto only prints once a year (Apr) — leave the other months blank so the line breaks rather than interpolating.
B32: CHART 3 — CURVE SLOPE vs 5Y RANGE
B33: Curve | C33: Current (bp) | D33: 5Y min | E33: 5Y max | F33: 5Y avg | G33: %ile in range
B34: JGB 2s10s | C34: 90 | D34: 5 | E34: 130 | F34: 62 | G34: =IFERROR((C34-D34)/(E34-D34),"") -> 0.68
B35: JGB 10s30s | C35: 100 | D35: 40 | E35: 165 | F35: 95 | G35: =IFERROR((C35-D35)/(E35-D35),"") -> 0.48
B36: UST 2s10s | C36: 55 | D36: -108 | E36: 160 | F36: 20 | G36: =IFERROR((C36-D36)/(E36-D36),"") -> 0.60820896
B37: Bund 2s10s | C37: 75 | D37: -75 | E37: 100 | F37: 15 | G37: =IFERROR((C37-D37)/(E37-D37),"") -> 0.85714286
B38: KTB 3s10s | C38: 40 | D38: -20 | E38: 95 | F38: 32 | G38: =IFERROR((C38-D38)/(E38-D38),"") -> 0.52173913
B39: The %ile column is the punchline — it says how much normalisation is left in each curve without you writing a sentence.

Sheet S3_CrossAsset
B2: SLIDE 3 — CROSS-ASSET BRIDGE
B3: Where the risk premium sits — asset-class calls only, no trade names
B6: CHART 1 — EQUITY RISK PREMIUM BY MARKET (earnings yield less 10Y local govt yield)
B7: Market | C7: Fwd P/E | D7: Earnings yield | E7: 10Y govt yield | F7: ERP | G7: 10Y avg ERP | H7: vs avg
B8: China (CSI 300) | C8: =S1_Equities!C8 -> 13.5 | D8: =IFERROR(1/C8,"") -> 0.074074074 | E8: =S2_FixedIncome!C8 -> 0.019 | F8: =D8-E8 -> 0.055074074 | G8: 0.048 | H8: =F8-G8 -> 0.0070740741
B9: Hong Kong (HSCEI) | C9: =S1_Equities!C9 -> 10.5 | D9: =IFERROR(1/C9,"") -> 0.095238095 | E9: =S2_FixedIncome!C9 -> 0.034 | F9: =D9-E9 -> 0.061238095 | G9: 0.062 | H9: =F9-G9 -> -0.00076190476
B10: Korea (KOSPI) | C10: =S1_Equities!C10 -> 11 | D10: =IFERROR(1/C10,"") -> 0.090909091 | E10: =S2_FixedIncome!C10 -> 0.031 | F10: =D10-E10 -> 0.059909091 | G10: 0.051 | H10: =F10-G10 -> 0.0089090909
B11: Japan (TOPIX) | C11: =S1_Equities!C11 -> 16 | D11: =IFERROR(1/C11,"") -> 0.0625 | E11: =S2_FixedIncome!C11 -> 0.019 | F11: =D11-E11 -> 0.0435 | G11: 0.043 | H11: =F11-G11 -> 0.0005
B12: Taiwan (TWSE) | C12: =S1_Equities!C12 -> 17.5 | D12: =IFERROR(1/C12,"") -> 0.057142857 | E12: =S2_FixedIncome!C12 -> 0.016 | F12: =D12-E12 -> 0.041142857 | G12: 0.035 | H12: =F12-G12 -> 0.0061428571
B13: Fwd P/E links to S1 and the 10Y links to S2 — edit the inputs there and this chart updates. Only the 10Y average ERP column is a manual input here.
B17: POSITIONING — ASSET CLASS LEVEL ONLY
B18: Asset class | C18: Call | D18: Supporting metric | E18: Value | F18: Source column
B19: China / HK equity | C19: OVERWEIGHT | D19: ERP vs 10Y avg (CSI 300) | E19: =H8 -> 0.0070740741 | F19: S3 ERP table
B20: Korea equity | C20: NEUTRAL | D20: 3M EPS revision ratio | E20: =S1_Equities!C20 -> 1.22 | F20: S1 chart 2
B21: Taiwan equity | C21: NEUTRAL | D21: Fwd P/E Z-score | E21: =S1_Equities!H12 -> 1 | F21: S1 chart 1
B22: Japan equity | C22: NEUTRAL | D22: ERP vs 10Y avg (TOPIX) | E22: =H11 -> 0.0005 | F22: S3 ERP table
B23: Japan duration | C23: UNDERWEIGHT | D23: 10Y real yield | E23: =S2_FixedIncome!E11 -> -0.006 | F23: S2 chart 1
B24: China duration | C24: NEUTRAL | D24: 10Y real yield | E24: =S2_FixedIncome!E8 -> 0.014 | F24: S2 chart 1
B26: Do NOT name CATL or the JGB trade on this slide. Asset-class calls only — the trade-idea slides that follow should feel like the conclusion, not the argument.
