Workbook

Sheet README
A1: H2 2026 Asian Cross-Asset — Risks Slide Data Pack
A2: Built 10-Aug-2026. Every series below feeds a chart on tabs R1_Oil / R2_BoJ / R3_China.
A4: HOW TO USE THIS FILE
A5: BLUE text | B5: A hardcoded number. Sourced in the note column beside it.
A6: YELLOW fill | B6: You must replace this. It is a placeholder or a terminal pull.
A7: BLACK text | B7: A formula. Do not overwrite — it will recalculate off your paste.
A8: GREEN text | B8: A link to another tab in this workbook.
A9: Grey italic | B9: Source note or instruction.
A12: WORKFLOW
A13: 1. Pull each series in the table below into a two-column block (date, value).
A14: 2. Paste into the yellow PASTE range on the matching tab. Keep the date column sorted ascending.
A15: 3. Formulas and charts update automatically. Do not insert rows inside a paste range — overwrite instead.
A16: 4. Check the Scenarios tab: it drives the three-scenario P&L strip at the bottom of the risks slide.
A19: DATA SOURCES
A20: Series | B20: Source | C20: Ticker / path | D20: Cost | E20: Notes
A21: Brent spot, daily | B21: EIA (free) or Bloomberg | C21: EIA series RBRTE / CO1 Comdty | D21: Free | E21: EIA 'Europe Brent Spot Price FOB' downloads as CSV, full history to 1987.
A22: Hormuz transit calls, daily | B22: IMF PortWatch | C22: portwatch.imf.org chokepoint dashboard | D22: Free | E22: THE key free series for Risk 1. Daily transit calls + 7d MA, downloadable. Pre-crisis baseline ~73/day.
A23: Hormuz transits, weekly detail | B23: Lloyd's List Intelligence | C23: Strait of Hormuz Brief (weekly) | D23: Paid | E23: Splits Iranian-linked vs non-Iranian traffic. Use only if you already have the subscription.
A24: USD/JPY, daily | B24: FRED (free) or Bloomberg | C24: FRED DEXJPUS / USDJPY Curncy | D24: Free | E24: FRED is daily NY close, no intraday. Fine for a monthly-frequency chart.
A25: MoF intervention amounts | B25: Japan Ministry of Finance | C25: mof.go.jp FX intervention data | D25: Free | E25: Monthly disclosure, published end-month. Confirms the intervention date markers.
A26: JGB par yields by tenor | B26: Japan MoF | C26: mof.go.jp historical interest rates | D26: Free | E26: You already use this on slide 8 — same source, daily, all tenors, back to 1974.
A27: Japan CPI core-core | B27: Statistics Bureau / e-Stat | C27: CPI ex fresh food & energy, nat'l | D27: Free | E27: National release ~19th of following month. Tokyo release ~end of prior month as the leading read.
A28: BoJ policy rate & forecasts | B28: Bank of Japan | C28: Outlook Report (Jan/Apr/Jul/Oct) | D28: Free | E28: The July-26 Outlook Report has the FY26 core-core forecast you use as a trigger.
A29: MSCI China price & fwd EPS | B29: Bloomberg / FactSet / IBES | C29: MXCN Index BEST_EPS | D29: Paid | E29: No free substitute at index level. Nearest free proxy: MCHI ETF price + holdings-weighted EPS.
A30: Earnings revision breadth | B30: Bloomberg / IBES | C30: MXCN, 3m up vs down revisions | D30: Paid | E30: If unavailable, substitute net FY2 EPS estimate change over 3m — same story, easier pull.
A31: China policy calendar | B31: Xinhua / State Council | C31: Politburo + CEWC announcements | D31: Free | E31: Hardcoded on R3_China. Verify dates before printing — they are announced with little notice.
A33: Anything marked Paid: pull it on the desk. Nothing in this pack requires paid data to produce a presentable chart — the free substitutes are named above.

Sheet Inputs
A1: Verified anchors and trigger levels
A2: Blue = verified as of 10-Aug-2026, source in column D. Yellow = your number, fill it in.
A4: Item | B4: Value | C4: Unit | D4: Source / note
A5: MARKET LEVELS
A6: Brent spot | B6: 83.55 | C6: USD/bbl | D6: 7-Aug-2026 settle. Trading Economics / Oilprice.
A7: Brent 52-week high | B7: 120.88 | C7: USD/bbl | D7: Intraday 30-Apr-2026. Forbes Advisor commodity page.
A8: Brent 52-week low | B8: 58.66 | C8: USD/bbl | D8: Intraday 16-Dec-2025. Forbes Advisor commodity page.
A9: Brent, 12m change | B9: 0.2547 | C9: % | D9: +25.5% y/y as of 7-Aug-2026.
A10: USD/JPY spot | B10: 157.65 | C10: JPY | D10: 7-Aug-2026. Trading Economics.
A11: USD/JPY, 1m change (yen stronger) | B11: -0.0304 | C11: % | D11: Yen +3.0% over the month to 7-Aug-2026, post-intervention.
A12: HORMUZ
A13: Transit calls, latest daily | B13: 2 | C13: vessels/day | D13: 2-Aug-2026, IMF PortWatch.
A14: Transit calls, pre-crisis baseline | B14: 73 | C14: vessels/day | D14: IMF PortWatch baseline. Other sources cite 88-130/day.
A15: Days closed as at 10-Aug-2026 | B15: 163 | C15: days | D15: Closed since 28-Feb-2026. Formula below cross-checks.
A16: JAPAN POLICY
A17: BoJ policy rate | B17: 0.01 | C17: % | D17: Hiked 25bp June-2026, held 31-Jul 8-1 (Takata dissent for 1.25%).
A18: BoJ FY2026 core-core forecast | B18: 0.022 | C18: % | D18: July-2026 Outlook Report. THIS IS YOUR STOP TRIGGER.
A19: BoJ FY2026 headline forecast | B19: 0.025 | C19: % | D19: Cut from 2.8% in the July-2026 Outlook Report.
A20: National core-core, latest | B20: 0.018 | C20: % | D20: May-2026. Statistics Bureau.
A21: Tokyo core-core, latest | B21: 0.02 | C21: % | D21: July-2026, up from 1.9% June. Leading indicator for national.
A22: JGB 2y yield | B22: 0.015 | C22: % | D22: Late-Jul-2026, ING. Only 50bp over policy rate.
A23: JGB 10y yield | B23: 0.027 | C23: % | D23: Late-Jul-2026, ING.
A24: Policy rate priced 2y forward | B24: 0.02 | C24: % | D24: OIS forwards, late-Jul-2026, ING.
A25: YOUR TRADE PARAMETERS — FILL IN
A26: 2s10s blended entry level | B26: 120.5 | C26: bp | D26: Blend of half at ~129bp post-BoJ and half at 112bp limit. Your slide 8.
A27: 2s10s target | B27: 160 | C27: bp | D27: Your slide 8.
A28: 2s10s stop | B28: 98 | C28: bp | D28: Your slide 8, hard stop.
A29: USD/JPY stop trigger | B29: 165 | C29: JPY | D29: Your slide 8. Note MoF already intervened jointly with the US in late July.
A30: Core-core stop trigger | B30: 0.022 | C30: % | D30: Your slide 8. Equals the BoJ's own FY26 forecast — say that.
A31: Risk budget, rates leg | B31: 0.3 | C31: % of book | D31: Your slide 8.
A32: Risk budget, China equity leg | C32: % of book | D32: NOT STATED on your deck — decide this before you present.
A34: Cross-check: days since Hormuz closed | B34: =DATE(2026,8,10)-DATE(2026,2,28) -> 163 | D34: If this does not equal the hardcoded 163 above, one of them is stale.

Sheet R1_Oil
A1: RISK 1 — Hormuz: the risk is two-sided, not one-sided
A2: The strait has been effectively closed since 28-Feb-2026 (2 transits/day vs a 73/day baseline). Brent has already round-tripped $58 - $121 - $84. Reopening is as big a shock as escalation.
A4: Block A — Brent monthly close, with scenario bands | H4: Block B — Oil beta of each book leg
A5: PASTE month-end Brent into columns A:B. Columns C:E are formulas that draw the scenario bands — leave them alone. | H5: PASTE weekly % changes. The betas below are what let you say 'the legs partially offset' with a number instead of a hand-wave.
A6: Date | B6: Brent | C6: Reopen case | D6: Base case | E6: Escalation case | F6: Flag | H6: Week ending | I6: Brent % | J6: China eq % | K6: 2s10s chg bp
A7: 45900 | B7: 66.5 | C7: =Bands!$B$4 -> 62 | D7: =Bands!$B$5 -> 84 | E7: =Bands!$B$6 -> 120 | F7: ESTIMATE - REPLACE | H7: EXAMPLE ROW - overwrite | I7: 0.052 | J7: -0.018 | K7: 4.5
A8: 45930 | B8: 67 | C8: =Bands!$B$4 -> 62 | D8: =Bands!$B$5 -> 84 | E8: =Bands!$B$6 -> 120 | F8: ESTIMATE - REPLACE
A9: 45961 | B9: 64.5 | C9: =Bands!$B$4 -> 62 | D9: =Bands!$B$5 -> 84 | E9: =Bands!$B$6 -> 120 | F9: ESTIMATE - REPLACE
A10: 45991 | B10: 62 | C10: =Bands!$B$4 -> 62 | D10: =Bands!$B$5 -> 84 | E10: =Bands!$B$6 -> 120 | F10: ESTIMATE - REPLACE
A11: 46022 | B11: 60 | C11: =Bands!$B$4 -> 62 | D11: =Bands!$B$5 -> 84 | E11: =Bands!$B$6 -> 120 | F11: Low of 58.66 on 16-Dec VERIFIED
A12: 46053 | B12: 70.69 | C12: =Bands!$B$4 -> 62 | D12: =Bands!$B$5 -> 84 | E12: =Bands!$B$6 -> 120 | F12: VERIFIED
A13: 46081 | B13: 72.48 | C13: =Bands!$B$4 -> 62 | D13: =Bands!$B$5 -> 84 | E13: =Bands!$B$6 -> 120 | F13: VERIFIED (week-end 20-Feb)
A14: 46112 | B14: 81.49 | C14: =Bands!$B$4 -> 62 | D14: =Bands!$B$5 -> 84 | E14: =Bands!$B$6 -> 120 | F14: VERIFIED (3-Mar close)
A15: 46142 | B15: 120.88 | C15: =Bands!$B$4 -> 62 | D15: =Bands!$B$5 -> 84 | E15: =Bands!$B$6 -> 120 | F15: VERIFIED intraday high
A16: 46173 | B16: 102 | C16: =Bands!$B$4 -> 62 | D16: =Bands!$B$5 -> 84 | E16: =Bands!$B$6 -> 120 | F16: ESTIMATE - REPLACE
A17: 46203 | B17: 88 | C17: =Bands!$B$4 -> 62 | D17: =Bands!$B$5 -> 84 | E17: =Bands!$B$6 -> 120 | F17: ESTIMATE - REPLACE (MoU reopening ~17-Jun)
A18: 46234 | B18: 78 | C18: =Bands!$B$4 -> 62 | D18: =Bands!$B$5 -> 84 | E18: =Bands!$B$6 -> 120 | F18: ESTIMATE - REPLACE
A19: 46241 | B19: 83.55 | C19: =Bands!$B$4 -> 62 | D19: =Bands!$B$5 -> 84 | E19: =Bands!$B$6 -> 120 | F19: VERIFIED
A24: Block C — Hormuz transit calls (IMF PortWatch, free)
A25: PASTE daily transit calls. This is the single best free series in the whole pack.
A26: Date | B26: Transits | C26: 7d MA | D26: Baseline
A27: 46073 | B27: 71 | C27: =IFERROR(AVERAGE(B27:B27),"") -> 71 | D27: =Inputs!$B$14 -> 73
A28: 46096 | B28: 8 | C28: =IFERROR(AVERAGE(B27:B28),"") -> 39.5 | D28: =Inputs!$B$14 -> 73
A29: 46127 | B29: 4 | C29: =IFERROR(AVERAGE(B27:B29),"") -> 27.666667 | D29: =Inputs!$B$14 -> 73
A30: 46157 | B30: 6 | C30: =IFERROR(AVERAGE(B27:B30),"") -> 22.25 | D30: =Inputs!$B$14 -> 73
A31: 46193 | B31: 34 | C31: =IFERROR(AVERAGE(B27:B31),"") -> 24.6 | D31: =Inputs!$B$14 -> 73
A32: 46208 | B32: 18 | C32: =IFERROR(AVERAGE(B27:B32),"") -> 23.5 | D32: =Inputs!$B$14 -> 73
A33: 46226 | B33: 10 | C33: =IFERROR(AVERAGE(B27:B33),"") -> 21.571429 | D33: =Inputs!$B$14 -> 73
A34: 46236 | B34: 2 | C34: =IFERROR(AVERAGE(B28:B34),"") -> 11.714286 | D34: =Inputs!$B$14 -> 73
A35: Anchor points only — 23-Jul and 2-Aug are verified PortWatch prints, the rest are illustrative. Replace with the full daily download. | H35: Computed betas
H36: Beta: China equity leg to Brent | I36: =IFERROR(SLOPE(J8:J33,I8:I33),"paste data") -> paste data | L36: Expect negative. This is your oil-shock loss on the equity leg.
H37: R-sq: China equity vs Brent | I37: =IFERROR(CORREL(J8:J33,I8:I33)^2,"paste data") -> paste data | L37: Below ~0.15 and the relationship is too weak to claim a hedge. Say so if it is.
H38: Beta: 2s10s (bp) to 1% Brent move | I38: =IFERROR(SLOPE(K8:K33,I8:I33),"paste data") -> paste data | L38: Expect positive. This is the offset.
H39: R-sq: 2s10s vs Brent | I39: =IFERROR(CORREL(K8:K33,I8:I33)^2,"paste data") -> paste data | L39: Same test.
H40: Net book P&L on a +20% Brent shock | I40: =IFERROR(I36*0.2*100,"paste data") -> paste data | L40: Rough, equity-leg only, in % terms. Refine with your own position sizes.

Sheet Bands
A1: Scenario band levels — edit these, the charts follow
A4: Reopening case Brent | B4: 62 | C4: Deal struck, transits normalise. Roughly the Dec-25 pre-war level.
A5: Base case Brent | B5: 84 | C5: Status quo: closed but contained, shuttling continues. Spot as of 7-Aug.
A6: Escalation case Brent | B6: 120 | C6: Re-run of the Apr-26 spike. Your Risk 1 trigger.
A7: Escalation trigger for the slide | B7: 95 | C7: The level at which you act, not the level you forecast.

Sheet R2_BoJ
A1: RISK 2 — BoJ defends the yen and the curve bear-flattens
A2: Policy rate 1.00%, held 8-1 on 31-Jul with a September hike signalled. The 2y at ~1.50% prices only 50bp over policy while forwards put the rate at 2% in two years. That gap is where the received leg loses.
A4: Block A — USD/JPY with the intervention zone | F4: Block B — Event study: what hawkish surprises do to 2s10s
A5: PASTE month-end USD/JPY into A:B. C:D draw the MoF action zone. | F5: THE most important table in this pack. Pull 1-day changes around each event from MoF JGB yields. Negative 2s10s = you lose.
A6: Date | B6: USD/JPY | C6: Watch 160 | D6: Stop 165 | F6: Event | G6: Date | H6: d2y bp | I6: d10y bp | J6: d2s10s bp
A7: 46022 | B7: 155 | C7: 160 | D7: =Inputs!$B$29 -> 165 | F7: BoJ hike to 0.75% | G7: 46010 | J7: =IF(COUNT(H7:I7)=2,I7-H7,"")
A8: 46053 | B8: 153 | C8: 160 | D8: =Inputs!$B$29 -> 165 | F8: BoJ hold, hawkish tone | G8: 46100 | J8: =IF(COUNT(H8:I8)=2,I8-H8,"")
A9: 46081 | B9: 156 | C9: 160 | D9: =Inputs!$B$29 -> 165 | F9: BoJ hike to 1.00% | G9: 46189 | J9: =IF(COUNT(H9:I9)=2,I9-H9,"")
A10: 46112 | B10: 157 | C10: 160 | D10: =Inputs!$B$29 -> 165 | F10: BoJ hold 8-1, Takata dissent | G10: 46234 | J10: =IF(COUNT(H10:I10)=2,I10-H10,"")
A11: 46142 | B11: 158 | C11: 160 | D11: =Inputs!$B$29 -> 165 | F11: Tamura 'hike every few months' | G11: 46234 | J11: =IF(COUNT(H11:I11)=2,I11-H11,"")
A12: 46173 | B12: 159.46 | C12: 160 | D12: =Inputs!$B$29 -> 165 | F12: Joint JP-US FX intervention | G12: 46234 | J12: =IF(COUNT(H12:I12)=2,I12-H12,"")
A13: 46203 | B13: 160.5 | C13: 160 | D13: =Inputs!$B$29 -> 165 | F13: NEXT: BoJ meeting | G13: 46283 | J13: =IF(COUNT(H13:I13)=2,I13-H13,"")
A14: 46234 | B14: 158.5 | C14: 160 | D14: =Inputs!$B$29 -> 165 | F14: NEXT: BoJ meeting | G14: 46324 | J14: =IF(COUNT(H14:I14)=2,I14-H14,"")
A15: 46241 | B15: 157.65 | C15: 160 | D15: =Inputs!$B$29 -> 165 | F15: Average 2s10s move on a hawkish event | J15: =IFERROR(AVERAGE(J7:J12),"paste data") -> paste data | K15: Excludes the two future meetings. If this average is materially negative, your entry rule of 'half after a BoJ hike' is buying into a flattening — say why that is the right side of it.
F17: Headroom to stop | G17: =Inputs!$B$26-Inputs!$B$28 -> 22.5 | K17: Entry minus stop, in bp. Compare with the average event move above: how many hawkish surprises can you absorb?
F18: Hawkish events to stop-out | G18: =IFERROR(ABS(G17/J15),"paste data") -> paste data | K18: If this is under ~3, the stop is too tight for the entry. A PM will do this division in their head — do it for them.
A20: Block C — Core-core inflation vs your stop trigger
A21: Your 2.2% trigger is exactly the BoJ's own FY2026 core-core forecast. Say that out loud.
A22: Date | B22: Nat'l core-core | C22: Tokyo core-core | D22: Trigger 2.2%
A23: 46053 | B23: 0.026 | D23: =Inputs!$B$18 -> 0.022
A24: 46081 | B24: 0.025 | C24: 0.023 | D24: =Inputs!$B$18 -> 0.022
A25: 46112 | B25: 0.025 | D25: =Inputs!$B$18 -> 0.022
A26: 46142 | B26: 0.019 | D26: =Inputs!$B$18 -> 0.022
A27: 46173 | B27: 0.018 | C27: 0.016 | D27: =Inputs!$B$18 -> 0.022
A28: 46203 | C28: 0.019 | D28: =Inputs!$B$18 -> 0.022
A29: 46234 | C29: 0.02 | D29: =Inputs!$B$18 -> 0.022
A30: National core-core prints ~19th of the following month. Tokyo leads it by about three weeks — that is your early warning.

Sheet R3_China
A1: RISK 3 — China policy disappointment: cheap stays cheap
A2: At 14x you are underwriting an earnings recovery. If forward EPS keeps falling, the multiple is not support — it is the symptom.
A4: Block A — Price vs forward EPS, both rebased to 100 | G4: Block B — Diagnostic
A5: PASTE MSCI China price and 12m forward EPS into B:C. D:E rebase automatically. If the EPS line falls while price rises, the whole move is re-rating — that is fragile. | G5: =IFERROR(D30/D7-1,"paste data") -> -1 | H5: Price change over window
A6: Date | B6: MXCN price | C6: 12m fwd EPS | D6: Price rebased | E6: EPS rebased | G6: =IFERROR(E30/E7-1,"paste data") -> -1 | H6: Fwd EPS change over window
A7: 45505 | B7: 60 | C7: 6.5 | D7: =IFERROR(B7/$B$7*100,"") -> 100 | E7: =IFERROR(C7/$C$7*100,"") -> 100 | G7: =IFERROR(G5-G6,"paste data") -> 0 | H7: Of which: re-rating
A8: 45536 | D8: =IFERROR(B8/$B$7*100,"") -> 0 | E8: =IFERROR(C8/$C$7*100,"") -> 0 | G8: =IF(G6<0,"EARNINGS STILL FALLING - value trap live","Earnings turning - thesis intact") -> EARNINGS STILL FALLING - value trap live | H8: Verdict
A9: 45566 | D9: =IFERROR(B9/$B$7*100,"") -> 0 | E9: =IFERROR(C9/$C$7*100,"") -> 0
A10: 45597 | D10: =IFERROR(B10/$B$7*100,"") -> 0 | E10: =IFERROR(C10/$C$7*100,"") -> 0 | G10: Block C — China policy calendar (your trigger dates)
A11: 45627 | D11: =IFERROR(B11/$B$7*100,"") -> 0 | E11: =IFERROR(C11/$C$7*100,"") -> 0 | G11: Date | H11: Event | I11: What would confirm the risk
A12: 45658 | D12: =IFERROR(B12/$B$7*100,"") -> 0 | E12: =IFERROR(C12/$C$7*100,"") -> 0 | G12: 46315 | H12: Q3 GDP | I12: Nominal growth still below real — deflation unbroken
A13: 45689 | D13: =IFERROR(B13/$B$7*100,"") -> 0 | E13: =IFERROR(C13/$C$7*100,"") -> 0 | G13: 46326 | H13: October Politburo | I13: No new demand-side measure, only supply-side 'anti-involution'
A14: 45717 | D14: =IFERROR(B14/$B$7*100,"") -> 0 | E14: =IFERROR(C14/$C$7*100,"") -> 0 | G14: 46368 | H14: Central Economic Work Conference | I14: Deficit target unchanged, no consumption transfer
A15: 45748 | D15: =IFERROR(B15/$B$7*100,"") -> 0 | E15: =IFERROR(C15/$C$7*100,"") -> 0 | G15: 46451 | H15: NPC / Two Sessions | I15: Growth target cut without offsetting stimulus
A16: 45778 | D16: =IFERROR(B16/$B$7*100,"") -> 0 | E16: =IFERROR(C16/$C$7*100,"") -> 0 | G16: Dates are indicative — Politburo and CEWC are announced at short notice. VERIFY before printing.
A17: 45809 | D17: =IFERROR(B17/$B$7*100,"") -> 0 | E17: =IFERROR(C17/$C$7*100,"") -> 0
A18: 45839 | D18: =IFERROR(B18/$B$7*100,"") -> 0 | E18: =IFERROR(C18/$C$7*100,"") -> 0
A19: 45870 | D19: =IFERROR(B19/$B$7*100,"") -> 0 | E19: =IFERROR(C19/$C$7*100,"") -> 0
A20: 45901 | D20: =IFERROR(B20/$B$7*100,"") -> 0 | E20: =IFERROR(C20/$C$7*100,"") -> 0
A21: 45931 | D21: =IFERROR(B21/$B$7*100,"") -> 0 | E21: =IFERROR(C21/$C$7*100,"") -> 0
A22: 45962 | D22: =IFERROR(B22/$B$7*100,"") -> 0 | E22: =IFERROR(C22/$C$7*100,"") -> 0
A23: 45992 | D23: =IFERROR(B23/$B$7*100,"") -> 0 | E23: =IFERROR(C23/$C$7*100,"") -> 0
A24: 46023 | D24: =IFERROR(B24/$B$7*100,"") -> 0 | E24: =IFERROR(C24/$C$7*100,"") -> 0
A25: 46054 | D25: =IFERROR(B25/$B$7*100,"") -> 0 | E25: =IFERROR(C25/$C$7*100,"") -> 0
A26: 46082 | D26: =IFERROR(B26/$B$7*100,"") -> 0 | E26: =IFERROR(C26/$C$7*100,"") -> 0
A27: 46113 | D27: =IFERROR(B27/$B$7*100,"") -> 0 | E27: =IFERROR(C27/$C$7*100,"") -> 0
A28: 46143 | D28: =IFERROR(B28/$B$7*100,"") -> 0 | E28: =IFERROR(C28/$C$7*100,"") -> 0
... A30: 46204 | D30: =IFERROR(B30/$B$7*100,"") -> 0 | E30: =IFERROR(C30/$C$7*100,"") -> 0
A31: EXAMPLE values in the first row only — overwrite the whole block.

Sheet Scenarios
A1: Three-scenario book P&L
A2: Fill the yellow cells with your own position sizes and expected moves. The point is not precision — it is that you have done it.
B4: Bear | C4: Base | D4: Bull | E4: Note
A5: SCENARIO DEFINITION
A6: Hormuz | B6: Escalation | C6: Closed, contained | D6: Reopening deal | E6: Your Risk 1, both tails.
A7: Brent | B7: 120 | C7: 84 | D7: 62 | E7: Links to the Bands tab.
A8: BoJ | B8: Hikes to defend JPY | C8: Sep hike, gradual | D8: On hold | E8: Your Risk 2.
A9: China policy | B9: CEWC disappoints | C9: Incremental easing | D9: Consumption package | E9: Your Risk 3.
A10: POSITION SIZES — FILL IN
A11: China equity leg, % of book | E11: Same number across all three columns.
A12: Rates leg, % of risk budget | E12: Slide 8 says 30%.
A13: EXPECTED MOVES — FILL IN
A14: China equity return, % | E14: Your estimate per scenario.
A15: 2s10s move, bp | E15: Bear should be at or through your 98bp stop.
A16: P&L
A17: Equity leg P&L, % of book | B17: =IFERROR(B11*B14,"fill inputs") -> 0 | C17: =IFERROR(C11*C14,"fill inputs") -> 0 | D17: =IFERROR(D11*D14,"fill inputs") -> 0
A18: Rates leg P&L, % of book | B18: =IFERROR(B12*B15/100,"fill inputs") -> 0 | C18: =IFERROR(C12*C15/100,"fill inputs") -> 0 | D18: =IFERROR(D12*D15/100,"fill inputs") -> 0
A19: TOTAL, % of book | B19: =IFERROR(B17+B18,"fill inputs") -> 0 | C19: =IFERROR(C17+C18,"fill inputs") -> 0 | D19: =IFERROR(D17+D18,"fill inputs") -> 0
A21: Falsifiability statement for the slide:
A22: The base case is Fed on hold, Hormuz closed but contained, and a gradual BoJ. The book loses on both legs simultaneously only if oil spikes AND the BoJ responds to imported inflation with a defensive hike. That is the one correlated tail.
